bytes.py
bytes-0.0.1.dev4.dist-info/DESCRIPTION.rst
bytes-0.0.1.dev4.dist-info/METADATA
bytes-0.0.1.dev4.dist-info/metadata.json
bytes-0.0.1.dev4.dist-info/RECORD
bytes-0.0.1.dev4.dist-info/top_level.txt
bytes-0.0.1.dev4.dist-info/WHEEL
_bytes/lists.py
_bytes/objects.py
_bytes/sections.py
_bytes/__init__.py
_bytes/formats/csv.py
_bytes/formats/__init__.py
